resort/__init__.py
resort/component/__init__.py
resort/component/docker.py
resort/component/glassfish.py
resort/component/maven.py
resort/component/packer.py
resort/component/postgresql.py
resort/component/resource.py
resort/component/vagrant.py
resort/engine/__init__.py
resort/engine/execution.py
resort/engine/task.py
resort/util/__init__.py
resort/util/jsons.py
resort-0.2.2.dist-info/DESCRIPTION.rst
resort-0.2.2.dist-info/METADATA
resort-0.2.2.dist-info/RECORD
resort-0.2.2.dist-info/WHEEL
resort-0.2.2.dist-info/metadata.json
resort-0.2.2.dist-info/top_level.txt
