Metadata-Version: 2.0
Name: resort
Version: 0.2.2
Summary: Component manager for software projects.
Home-page: https://github.com/miquelo/resort
Author: "Miquel A. Ferran Gonzalez"
Author-email: miquel.ferran.gonzalez@gmail.com
License: LICENSE.txt
Platform: UNKNOWN
Requires-Dist: colorama (>=0.3.3)
